test_helper_spark/__init__.py
test_helper_spark/test_helper_spark.py
test_helper_spark-0.3.dist-info/DESCRIPTION.rst
test_helper_spark-0.3.dist-info/METADATA
test_helper_spark-0.3.dist-info/RECORD
test_helper_spark-0.3.dist-info/WHEEL
test_helper_spark-0.3.dist-info/metadata.json
test_helper_spark-0.3.dist-info/top_level.txt
