Metadata-Version: 2.0
Name: test-helper-spark
Version: 0.3
Summary: A testing helper for "Intro to Big Data with Apache Spark" course
Home-page: https://github.com/rospotniuk/test_helper
Author: Dmytro Fesenko, Volodymyr Rospotniuk
Author-email: fesenkogithub@gmail.com, rospotniuk@gmail.com
License: UNKNOWN
Keywords: testing,autograder,spark
Platform: UNKNOWN
